safeds_datasets/__init__.py
safeds_datasets/image/__init__.py
safeds_datasets/image/_mnist/__init__.py
safeds_datasets/image/_mnist/_mnist.py
safeds_datasets/tabular/__init__.py
safeds_datasets/tabular/_house_sales/__init__.py
safeds_datasets/tabular/_house_sales/_house_sales.py
safeds_datasets/tabular/_house_sales/data/house_sales.csv
safeds_datasets/tabular/_titanic/__init__.py
safeds_datasets/tabular/_titanic/_titanic.py
safeds_datasets/tabular/_titanic/data/titanic.csv
safeds_datasets/tabular/containers/__init__.py
safeds_datasets/tabular/containers/_table_with_descriptions.py
safe_ds_datasets-0.19.0.dist-info/LICENSE
safe_ds_datasets-0.19.0.dist-info/METADATA
safe_ds_datasets-0.19.0.dist-info/WHEEL
safe_ds_datasets-0.19.0.dist-info/RECORD
