Metadata-Version: 2.1
Name: safe-ds-datasets
Version: 0.19.0
Summary: Ready-to-use datasets for the Safe-DS Python library.
Home-page: https://github.com/Safe-DS/Datasets
License: MIT
Keywords: data-science,datasets,machine-learning
Author: Lars Reimann
Author-email: mail@larsreimann.com
Requires-Python: >=3.11,<3.13
Classifier: License :: OSI Approved :: MIT License
Classifier: Programming Language :: Python :: 3
Classifier: Programming Language :: Python :: 3.11
Classifier: Programming Language :: Python :: 3.12
Requires-Dist: safe-ds (>=0.24,<0.29)
Project-URL: Documentation, https://datasets.safe-ds.com
Project-URL: Repository, https://github.com/Safe-DS/Datasets
